ndasynapse/__init__.py
ndasynapse/__version__.py
ndasynapse/nda.py
ndasynapse/synapse.py
ndasynapse-1.0.2.data/scripts/manifest_guid_data.py
ndasynapse-1.0.2.data/scripts/manifest_to_synapse.py
ndasynapse-1.0.2.data/scripts/nda_to_synapse_manifest.py
ndasynapse-1.0.2.data/scripts/query-nda
ndasynapse-1.0.2.dist-info/METADATA
ndasynapse-1.0.2.dist-info/WHEEL
ndasynapse-1.0.2.dist-info/top_level.txt
ndasynapse-1.0.2.dist-info/RECORD
